{"Date":"21.01.2013","Time":"06:00","Name":"Vesti","Age":"0","Type":"Broadcast","TV":"RTS1"}{"Date":"21.01.2013","Time":"06:05","Name":"Jutarnji program","Age":"0","Type":"Broadcast","TV":"RTS1"}{"Date":"21.01.2013","Time":"08:00","Name":"Jutarnji dnevnik","Age":"0","Type":"Broadcast","TV":"RTS1"}{"Date":"21.01.2013","Time":"08:15","Name":"Jutarnji program","Age":"0","Type":"Broadcast","TV":"RTS1"}{"Date":"21.01.2013","Time":"09:00","Name":"Vesti","Age":"0","Type":"Broadcast","TV":"RTS1"}{"Date":"21.01.2013","Time":"09:05","Name":"Dome, slatki dome, tv serija","Age":"12","Type":"TV Show","TV":"RTS1"}{"Date":"21.01.2013","Time":"09:45","Name":"Gastronomad","Age":"0","Type":"Show","TV":"RTS1"}{"Date":"21.01.2013","Time":"10:00","Name":"Vesti","Age":"0","Type":"Broadcast","TV":"RTS1"}{"Date":"21.01.2013","Time":"10:05","Name":"Lov i ribolov: Na severu Evrope","Age":"0","Type":"Show","TV":"RTS1"}{"Date":"21.01.2013","Time":"10:35","Name":"Eko karavan","Age":"0","Type":"Show","TV":"RTS1"}{"Date":"21.01.2013","Time":"11:05","Name":"Vesti","Age":"0","Type":"Broadcast","TV":"RTS1"}{"Date":"21.01.2013","Time":"11:09","Name":"313.","Age":"0","Type":"Show","TV":"RTS1"}{"Date":"21.01.2013","Time":"12:00","Name":"Dnevnik","Age":"0","Type":"Broadcast","TV":"RTS1"}{"Date":"21.01.2013","Time":"12:15","Name":"Sport plus","Age":"0","Type":"Sports Event","TV":"RTS1"}{"Date":"21.01.2013","Time":"12:25","Name":"Vreme, stanje na putevima","Age":"0","Type":"Broadcast","TV":"RTS1"}{"Date":"21.01.2013","Time":"12:30","Name":"Mesto zlo\u010dina: Njujork, ameri\u010dka serija","Age":"16","Type":"TV Show","TV":"RTS1"}{"Date":"21.01.2013","Time":"13:15","Name":"Evronet","Age":"0","Type":"Show","TV":"RTS1"}{"Date":"21.01.2013","Time":"13:20","Name":"Renta dete, ameri\u010dki film","Age":"12","Type":"Movie","TV":"RTS1"}{"Date":"21.01.2013","Time":"14:45","Name":"I ja imam talenat","Age":"0","Type":"Show","TV":"RTS1"}{"Date":"21.01.2013","Time":"15:10","Name":"Ovo je Srbija","Age":"0","Type":"Show","TV":"RTS1"}{"Date":"21.01.2013","Time":"15:55","Name":"Pozori\u0161te u ku\u0107i, tv serija","Age":"12","Type":"TV Show","TV":"RTS1"}{"Date":"21.01.2013","Time":"17:00","Name":"Dnevnik RT Vojvodina","Age":"0","Type":"Broadcast","TV":"RTS1"}{"Date":"21.01.2013","Time":"17:20","Name":"\u0160ta radite, bre","Age":"0","Type":"Broadcast","TV":"RTS1"}{"Date":"21.01.2013","Time":"17:45","Name":"Beogradska hronika","Age":"0","Type":"Show","TV":"RTS1"}{"Date":"21.01.2013","Time":"18:25","Name":"Oko","Age":"0","Type":"Broadcast","TV":"RTS1"}{"Date":"21.01.2013","Time":"19:00","Name":"Slagalica, kviz","Age":"0","Type":"Show","TV":"RTS1"}{"Date":"21.01.2013","Time":"19:21","Name":"Vreme, stanje na putevima","Age":"0","Type":"Broadcast","TV":"RTS1"}{"Date":"21.01.2013","Time":"19:30","Name":"Dnevnik","Age":"0","Type":"Broadcast","TV":"RTS1"}{"Date":"21.01.2013","Time":"20:05","Name":"Bolji \u017eivot, tv serija","Age":"12","Type":"TV Show","TV":"RTS1"}{"Date":"21.01.2013","Time":"20:50","Name":"Ma nije on takav , doma\u0107i film","Age":"14","Type":"Movie","TV":"RTS1"}{"Date":"21.01.2013","Time":"22:20","Name":"Vesti","Age":"0","Type":"Broadcast","TV":"RTS1"}{"Date":"21.01.2013","Time":"22:25","Name":"Mesto zlo\u010dina: Njujork, ameri\u010dka serija","Age":"16","Type":"TV Show","TV":"RTS1"}{"Date":"21.01.2013","Time":"23:10","Name":"Dnevnik","Age":"0","Type":"Broadcast","TV":"RTS1"}{"Date":"21.01.2013","Time":"23:25","Name":"Evronet","Age":"0","Type":"Show","TV":"RTS1"}{"Date":"21.01.2013","Time":"23:35","Name":"Misterije Hejvena, ameri\u010dka serija","Age":"16","Type":"TV Show","TV":"RTS1"}{"Date":"21.01.2013","Time":"00:20","Name":"\u017divi svoj \u017eivot, ameri\u010dki film","Age":"12","Type":"Movie","TV":"RTS1"}{"Date":"21.01.2013","Time":"01:54","Name":"Dome, slatki dome, tv serija","Age":"12","Type":"TV Show","TV":"RTS1"}{"Date":"21.01.2013","Time":"02:00","Name":"Vesti (03.00,04.00,05.00)","Age":"0","Type":"Broadcast","TV":"RTS1"}{"Date":"21.01.2013","Time":"02:39","Name":"313.","Age":"0","Type":"Show","TV":"RTS1"}{"Date":"21.01.2013","Time":"03:30","Name":"Eko karavan","Age":"0","Type":"Show","TV":"RTS1"}{"Date":"21.01.2013","Time":"04:03","Name":"Oko","Age":"0","Type":"Broadcast","TV":"RTS1"}{"Date":"21.01.2013","Time":"04:33","Name":"Lov i ribolov: Na severu Evrope","Age":"0","Type":"Show","TV":"RTS1"}{"Date":"21.01.2013","Time":"05:06","Name":"Bolji \u017eivot, tv serija","Age":"12","Type":"TV Show","TV":"RTS1"}{"Date":"21.01.2013","Time":"05:47","Name":"Verski kalendar","Age":"0","Type":"Show","TV":"RTS1"}